preepiseizures_api_client/__init__.py
preepiseizures_api_client/__version__.py
preepiseizures_api_client/client.py
preepiseizures_api_client-0.1.1.dist-info/licenses/LICENSE
preepiseizures_api_client-0.1.1.dist-info/METADATA
preepiseizures_api_client-0.1.1.dist-info/WHEEL
preepiseizures_api_client-0.1.1.dist-info/top_level.txt
preepiseizures_api_client-0.1.1.dist-info/RECORD
