Metadata-Version: 2.4
Name: preepiseizures_api_client
Version: 0.1.1
Summary: Short description.
Author-email: Ana Sofia Carmo <anascacais@gmail.com>
License: BSD 3-Clause License
Project-URL: Repository, https://github.com/anascacais/preepiseizures-api-client
Classifier: Programming Language :: Python :: 3
Classifier: Operating System :: OS Independent
License-File: LICENSE
Dynamic: license-file
